astro_metadata_translator/__init__.py
astro_metadata_translator/file_helpers.py
astro_metadata_translator/headers.py
astro_metadata_translator/indexing.py
astro_metadata_translator/observationGroup.py
astro_metadata_translator/observationInfo.py
astro_metadata_translator/properties.py
astro_metadata_translator/py.typed
astro_metadata_translator/tests.py
astro_metadata_translator/translator.py
astro_metadata_translator/version.py
astro_metadata_translator/bin/__init__.py
astro_metadata_translator/bin/translate.py
astro_metadata_translator/bin/writeindex.py
astro_metadata_translator/bin/writesidecar.py
astro_metadata_translator/cli/__init__.py
astro_metadata_translator/cli/astrometadata.py
astro_metadata_translator/corrections/CFHT/README.md
astro_metadata_translator/corrections/DECam/README.md
astro_metadata_translator/corrections/HSC/HSC-HSCA00042600.yaml
astro_metadata_translator/corrections/HSC/HSC-HSCA00120200.yaml
astro_metadata_translator/corrections/HSC/HSC-HSCA00120400.yaml
astro_metadata_translator/corrections/HSC/HSC-HSCA00120600.yaml
astro_metadata_translator/corrections/HSC/HSC-HSCA00120800.yaml
astro_metadata_translator/corrections/HSC/HSC-HSCA00121000.yaml
astro_metadata_translator/corrections/HSC/HSC-HSCA00121200.yaml
astro_metadata_translator/corrections/HSC/HSC-HSCA00121400.yaml
astro_metadata_translator/corrections/HSC/HSC-HSCA00121600.yaml
astro_metadata_translator/corrections/HSC/HSC-HSCA00121800.yaml
astro_metadata_translator/corrections/HSC/HSC-HSCA00122000.yaml
astro_metadata_translator/corrections/HSC/HSC-HSCA00122800.yaml
astro_metadata_translator/corrections/HSC/HSC-HSCA00123000.yaml
astro_metadata_translator/corrections/HSC/HSC-HSCA00123200.yaml
astro_metadata_translator/corrections/HSC/HSC-HSCA00123800.yaml
astro_metadata_translator/corrections/HSC/HSC-HSCA00124000.yaml
astro_metadata_translator/corrections/HSC/HSC-HSCA00124200.yaml
astro_metadata_translator/corrections/HSC/HSC-HSCA00124400.yaml
astro_metadata_translator-30.0.0.dist-info/licenses/LICENSE
astro_metadata_translator-30.0.0.dist-info/METADATA
astro_metadata_translator-30.0.0.dist-info/WHEEL
astro_metadata_translator-30.0.0.dist-info/entry_points.txt
astro_metadata_translator-30.0.0.dist-info/top_level.txt
astro_metadata_translator-30.0.0.dist-info/zip-safe
astro_metadata_translator-30.0.0.dist-info/RECORD
