Metadata-Version: 2.4
Name: astro-metadata-translator
Version: 30.0.0
Summary: A translator for astronomical metadata.
Author-email: Rubin Observatory Data Management <dm-admin@lists.lsst.org>
License-Expression: BSD-3-Clause
Project-URL: Homepage, https://github.com/lsst/astro_metadata_translator
Keywords: lsst
Classifier: Intended Audience :: Science/Research
Classifier: Topic :: Scientific/Engineering :: Astronomy
Classifier: Operating System :: OS Independent
Classifier: Programming Language :: Python :: 3
Classifier: Programming Language :: Python :: 3.14
Classifier: Programming Language :: Python :: 3.13
Classifier: Programming Language :: Python :: 3.12
Classifier: Programming Language :: Python :: 3.11
Requires-Python: >=3.11.0
License-File: LICENSE
Requires-Dist: astropy>=3.0.5
Requires-Dist: pyyaml>=3.13
Requires-Dist: lsst-resources
Requires-Dist: fsspec
Requires-Dist: click>=8
Provides-Extra: test
Requires-Dist: pytest; extra == "test"
Dynamic: license-file
